ddop2/__init__.py
ddop2/_modidx.py
ddop2/core.py
ddop2/datasets/__init__.py
ddop2/datasets/_base.py
ddop2/datasets/data/SID_data.csv
ddop2/datasets/data/SID_target.csv
ddop2/datasets/data/bakery_data.csv
ddop2/datasets/data/bakery_target.csv
ddop2/datasets/data/wuerzbaeck_data.csv
ddop2/datasets/data/wuerzbaeck_target.csv
ddop2/datasets/data/yaz_data.csv
ddop2/datasets/data/yaz_target.csv
ddop2/datasets/data/zenbite_data.csv
ddop2/datasets/data/zenbite_drinks.csv
ddop2/datasets/data/zenbite_target.csv
ddop2/datasets/descr/SID.rst
ddop2/datasets/descr/bakery.rst
ddop2/datasets/descr/wuerzbaeck.rst
ddop2/datasets/descr/yaz.rst
ddop2/datasets/descr/zenbite.rst
ddop2/dscm/__init__.py
ddop2/dscm/cost.py
ddop2/dscm/curly_brace.py
ddop2/dscm/plots.py
ddop2/metrics/__init__.py
ddop2/metrics/_costs.py
ddop2/metrics/_scorer.py
ddop2/newsvendor/_DeepLearningNewsvendor.py
ddop2/newsvendor/_ExponentialSmoothingNewsvendor.py
ddop2/newsvendor/_LinearRegressionNewsvendor.py
ddop2/newsvendor/_SampleAverageApproximationNewsvendor.py
ddop2/newsvendor/_WeightedNewsvendor.py
ddop2/newsvendor/__init__.py
ddop2/newsvendor/_base.py
ddop2/utils/__init__.py
ddop2/utils/validation.py
ddop2-0.0.22.dist-info/LICENSE
ddop2-0.0.22.dist-info/METADATA
ddop2-0.0.22.dist-info/WHEEL
ddop2-0.0.22.dist-info/entry_points.txt
ddop2-0.0.22.dist-info/top_level.txt
ddop2-0.0.22.dist-info/RECORD
