Metadata-Version: 2.1
Name: ddop2
Version: 0.0.22
Summary: Restructuring of ddop
Home-page: https://github.com/opimwue/ddop2
Author: kaiguender
Author-email: kai.guender@yahoo.de
License: Apache Software License 2.0
Keywords: nbdev jupyter notebook python
Platform: UNKNOWN
Classifier: Development Status :: 4 - Beta
Classifier: Intended Audience :: Developers
Classifier: Natural Language :: English
Classifier: Programming Language :: Python :: 3.7
Classifier: Programming Language :: Python :: 3.8
Classifier: Programming Language :: Python :: 3.9
Classifier: Programming Language :: Python :: 3.10
Classifier: License :: OSI Approved :: Apache Software License
Requires-Python: >=3.7
License-File: LICENSE
Requires-Dist: fastcore
Requires-Dist: torch
Requires-Dist: numpy
Requires-Dist: scipy
Requires-Dist: pandas
Requires-Dist: statsmodels
Requires-Dist: scikit-learn
Requires-Dist: pulp
Requires-Dist: mpmath
Requires-Dist: matplotlib
Requires-Dist: torchaudio
Requires-Dist: torchvision
Requires-Dist: ipywidgets
Requires-Dist: seaborn
Provides-Extra: dev
